{
  "skill_id": "evo_skill_a3f2a213ec2a",
  "name": "island_cycling_travel",
  "description": "提供海岛旅游、环岛电动车骑行及沙滩拾贝等户外游玩活动的规划与推荐。",
  "when_to_use": "当用户询问海岛游玩攻略、环岛骑行路线、电动车租赁游玩建议或沙滩活动时使用。",
  "trigger_keywords": [
    "海岛游",
    "环岛骑行",
    "电动车租赁",
    "沙滩活动",
    "捡贝壳"
  ],
  "tags": [
    "旅游",
    "户外",
    "骑行",
    "海岛",
    "沙滩活动"
  ],
  "example_queries": [
    "我喜欢去湄洲岛玩，里面有很多好玩的地方，沿着小岛去东口找租一辆电动车，然后一边骑行，一边玩。早上可以捡贝壳"
  ],
  "usage_count": 1,
  "version": 1,
  "content": "# Island Cycling Travel\n\n## Description\n提供海岛旅游、环岛电动车骑行及沙滩拾贝等户外游玩活动的规划与推荐。\n\n## When to Use\n当用户询问海岛游玩攻略、环岛骑行路线、电动车租赁游玩建议或沙滩活动时使用。\n\n## Trigger Keywords\n- 海岛游\n- 环岛骑行\n- 电动车租赁\n- 沙滩活动\n- 捡贝壳\n\n## Procedure\n1. 确认用户的目标海岛、出行时间及游玩偏好。\n2. 推荐海岛环岛电动车骑行路线及租赁点信息（如热门区域的租车点）。\n3. 提供海岛特色户外活动建议，如晨间沙滩拾贝、沿海岸线骑行观光等。\n4. 整合行程，输出包含交通、游玩和活动的完整攻略。\n\n## Example Queries\n- 我喜欢去湄洲岛玩，里面有很多好玩的地方，沿着小岛去东口找租一辆电动车，然后一边骑行，一边玩。早上可以捡贝壳\n- 推荐一个适合环岛骑行的海岛，顺便说说哪里可以租电动车。\n- 海岛游有什么好玩的？想早上在沙滩捡贝壳，白天骑车环岛。",
  "created_at": "2026-04-26T02:58:46.348740+00:00",
  "updated_at": "2026-04-26T02:58:46.348740+00:00",
  "last_query": "我喜欢去湄洲岛玩，里面有很多好玩的地方，沿着小岛去东口找租一辆电动车，然后一边骑行，一边玩。早上可以捡贝壳"
}